awsreplicate/__init__.py
awsreplicate/config.py
awsreplicate/dynamodb_replicator.py
awsreplicate/s3_replicator.py
awsreplicate/utils/__init__.py
awsreplicate/utils/concurrency.py
awsreplicate/utils/logging.py
awsreplicate/utils/retry.py
awsreplicate-0.1.1.dist-info/METADATA
awsreplicate-0.1.1.dist-info/WHEEL
awsreplicate-0.1.1.dist-info/top_level.txt
awsreplicate-0.1.1.dist-info/RECORD
