Metadata-Version: 2.4
Name: awsreplicate
Version: 0.1.1
Summary: Lightweight SDK for cross-region data replication in AWS
Author-email: Kalyanasundaram K <kkalyan2701@gmail.com>
License: MIT
Project-URL: Homepage, https://github.com/yourusername/awsreplicate
Project-URL: Documentation, https://github.com/yourusername/awsreplicate#readme
Project-URL: Repository, https://github.com/yourusername/awsreplicate
Classifier: Development Status :: 3 - Alpha
Classifier: Intended Audience :: Developers
Classifier: License :: OSI Approved :: MIT License
Classifier: Programming Language :: Python :: 3
Classifier: Programming Language :: Python :: 3.9
Classifier: Programming Language :: Python :: 3.10
Classifier: Programming Language :: Python :: 3.11
Classifier: Programming Language :: Python :: 3.12
Requires-Python: >=3.9
Requires-Dist: boto3>=1.28.0
Requires-Dist: aioboto3>=12.0.0
Requires-Dist: tenacity>=8.2.0
Requires-Dist: smart-open>=6.4.0
Requires-Dist: structlog>=23.1.0
Provides-Extra: dev
Requires-Dist: pytest>=7.4.0; extra == "dev"
Requires-Dist: pytest-asyncio>=0.21.0; extra == "dev"
Requires-Dist: moto[dynamodb,s3]>=4.2.0; extra == "dev"
Requires-Dist: black>=23.7.0; extra == "dev"
Requires-Dist: ruff>=0.0.285; extra == "dev"
